input_audio/VERSION
input_audio/__init__.py
input_audio-0.2.0.dist-info/LICENSE
input_audio-0.2.0.dist-info/METADATA
input_audio-0.2.0.dist-info/WHEEL
input_audio-0.2.0.dist-info/RECORD
