Metadata-Version: 2.3
Name: input-audio
Version: 0.2.0
Summary: Python input audio.
License: MIT
Author: Allen Chou
Author-email: f1470891079@gmail.com
Requires-Python: >=3.11,<4
Classifier: License :: OSI Approved :: MIT License
Classifier: Programming Language :: Python :: 3
Classifier: Programming Language :: Python :: 3.11
Classifier: Programming Language :: Python :: 3.12
Classifier: Programming Language :: Python :: 3.13
Requires-Dist: dictpress (>=0.3.0)
Requires-Dist: durl-py (>=0.1.1)
Requires-Dist: logging-bullet-train
Requires-Dist: noisereduce (>=3,<4)
Requires-Dist: numpy (>=2,<3)
Requires-Dist: openai (>=1,<2)
Requires-Dist: openai-agents (>=0.1.0,<1.0.0)
Requires-Dist: pyaudio (>=0.2,<0.3)
Requires-Dist: pydantic (>=2)
Requires-Dist: silero-vad (>=5,<6)
Requires-Dist: str-or-none
Project-URL: Homepage, https://github.com/allen2c/input_audio
Project-URL: Repository, https://github.com/allen2c/input_audio
